<step title="BackgroundTrace" date="2025-12-03T14:53:16.524" instance="acfa2b" url="/api/zipdeploy" method="POST" >
  <step title="Creating temporary deployment - FetchDeploymentManager" date="2025-12-03T14:53:16.598" /><!-- duration: 9ms -->
  <step title="Creating temporary deployment" date="2025-12-03T14:53:16.610" /><!-- duration: 70ms -->
  <step title="Performing fetch based deployment" date="2025-12-03T14:53:16.718" >
    <step title="Cleaning up temp folders from previous zip deployments and extracting pushed zip file /tmp/zipdeploy/c1e4421b-2027-4380-b9f0-32e179bafd80.zip (0.37 MB) to /tmp/zipdeploy/extracted" date="2025-12-03T14:53:17.933" >
      <step title="ChmodRecursive Process exited with total time taken in ms: 242" date="2025-12-03T14:53:18.287" /><!-- duration: 17ms -->
    </step><!-- duration: 439ms -->
    <step title="Deployment timer started" date="2025-12-03T14:53:20.446" >
      <step title="DeploymentManager.Deploy(id:e72a8cc4-c1e4-4911-a327-454731df742f)" date="2025-12-03T14:53:20.459" >
        <step title="Collecting changeset information" date="2025-12-03T14:53:20.503" /><!-- duration: 256ms -->
        <step title="Updating submodules" date="2025-12-03T14:53:20.780" /><!-- duration: 1239ms -->
        <step title="Determining deployment builder" date="2025-12-03T14:53:22.356" >
          <step title="Builder is OryxBuilder" date="2025-12-03T14:53:22.381" /><!-- duration: 11ms -->
        </step><!-- duration: 55ms -->
        <step title="PreDeployment: context.CleanOutputPath False" date="2025-12-03T14:53:23.635" >
          <step title="PreDeployment: context.OutputPath /home/site/wwwroot" date="2025-12-03T14:53:23.818" >
            <step title="Building" date="2025-12-03T14:53:24.170" >
              <step title="Executing external process" date="2025-12-03T14:53:25.330" type="process" path="bash" arguments="-c &quot;oryx build /tmp/zipdeploy/extracted -o /home/site/wwwroot --platform python --platform-version 3.11 -p virtualenv_name=antenv --log-file /tmp/build-debug.log  -i /tmp/8de327bb485fd18 --compress-destination-dir | tee /tmp/oryx-build.log ; exit $PIPESTATUS &quot;" /><!-- duration: 120509ms -->
              <step title="Using PythonDeploymentLogParser" date="2025-12-03T14:55:26.773" /><!-- duration: 49ms -->
              <step title="Triggering recycle (preview mode disabled)." date="2025-12-03T14:55:28.561" /><!-- duration: 7ms -->
              <step title="Modified file to trigger a restart of the app container." date="2025-12-03T14:55:28.612" /><!-- duration: 3ms -->
              <step title="Skip function trigger and logicapp sync because function is not enabled." date="2025-12-03T14:55:28.620" /><!-- duration: 3ms -->
              <step title="Purge deployment items" date="2025-12-03T14:55:30.457" >
                <step title="Remove 3e538925-, Success, received at 12/03/2025 11:36:18" date="2025-12-03T14:55:30.536" /><!-- duration: 3ms -->
              </step><!-- duration: 87ms -->
            </step><!-- duration: 126478ms -->
          </step><!-- duration: 126839ms -->
          <step title="Cleaning up temp files" date="2025-12-03T14:55:30.659" /><!-- duration: 2329ms -->
          <step title="Cleaning up temp files" date="2025-12-03T14:55:33.010" /><!-- duration: 522ms -->
          <step title="Reloading status file with latest updates" date="2025-12-03T14:55:33.591" >
            <step title="WebHooksManager.PublishEventAsync: PostDeployment" date="2025-12-03T14:55:33.597" /><!-- duration: 79ms -->
          </step><!-- duration: 91ms -->
          <step title="Cleaning up temporary deployment - fetch deployment was successful" date="2025-12-03T14:55:33.688" /><!-- duration: 7ms -->
        </step><!-- duration: 130122ms -->
      </step><!-- duration: 133321ms -->
